grokpub/__init__.py
grokpub/field.py
grokpub/response/__init__.py
grokpub/response/response.py
grokpub/schema/__init__.py
grokpub/schema/action.py
grokpub/schema/article.py
grokpub/schema/audio.py
grokpub/schema/channel.py
grokpub/schema/gallery.py
grokpub/schema/message.py
grokpub/schema/rss.py
grokpub/schema/tweet.py
grokpub/schema/user.py
grokpub/schema/video.py
grokpub/utils/__init__.py
grokpub/utils/unique.py
grokpub-0.1.1.dist-info/WHEEL
grokpub-0.1.1.dist-info/METADATA
grokpub-0.1.1.dist-info/RECORD
