Metadata-Version: 2.1
Name: grokpub
Version: 0.1.1
Summary: 
License: MIT
Author: Gaoddy
Author-email: gaoddy@gmail.com
Requires-Python: >=3.9,<4.0
Classifier: License :: OSI Approved :: MIT License
Classifier: Programming Language :: Python :: 3
Classifier: Programming Language :: Python :: 3.10
Classifier: Programming Language :: Python :: 3.9
Requires-Dist: orjson (>=3.7.11,<4.0.0)
Requires-Dist: pydantic (>=1.9.1,<2.0.0)
